packagesetup/__init__.py
packagesetup-0.1.1.dist-info/METADATA
packagesetup-0.1.1.dist-info/WHEEL
packagesetup-0.1.1.dist-info/top_level.txt
packagesetup-0.1.1.dist-info/RECORD
