Metadata-Version: 2.1
Name: packagesetup
Version: 0.1.1
Summary: A package meant to help faciliate the setup.py aspect of Python package distribution.
Home-page: UNKNOWN
Author: Prerit Das
Author-email: <preritdas@gmail.com>
License: UNKNOWN
Keywords: python,tools,setup,distribution
Platform: UNKNOWN
Classifier: Programming Language :: Python :: 3
Classifier: Operating System :: Unix
Classifier: Operating System :: MacOS :: MacOS X
Classifier: Operating System :: Microsoft :: Windows
Requires-Dist: wheel
Requires-Dist: setuptools
